{
  "schema_version": 1,
  "id": "001-consolidate-duplicate-cli-commands-idea-and-ideas",
  "title": "Consolidate duplicate CLI commands 'idea' and 'ideas'",
  "section": "documentation",
  "state": "implementing",
  "overview": "The codebase has two CLI commands ('idea' and 'ideas') that perform identical functionality, causing user confusion\n\n**Motivation:** Having two commands for the same purpose is confusing for users. Since the project hasn't reached 1.0 yet, it's safe to remove the duplicate command entirely.\n\n**Success criteria:**\n- Only 'ideas' command exists in CLI\n- All references to 'idea' command removed from codebase\n- No breaking changes to existing functionality\n- Documentation only references 'ideas' command\n\n**Technical constraints:**\n- Must remove 'idea' command entirely from src/index.ts\n- Cannot introduce breaking changes to the 'ideas' command functionality\n- Tests must continue to pass\n\n**In scope:**\n- Remove 'idea' command registration from CLI definition in src/index.ts\n- Search codebase for any lingering references to 'idea' CLI command\n- Update documentation if needed (README, AGENTS.md, etc.)\n- Update any tests that reference the 'idea' command\n**Out of scope:**\n- Changing the 'idea' state name used internally in the workflow\n- Modifying the 'ideas' command functionality\n\n**Signals:** priority: medium, urgency: low",
  "branch": null,
  "pr_url": null,
  "pr_number": null,
  "last_error": "Git pre-flight check failed:\n\nâ€¢ There are uncommitted changes in the working directory\n    Run `git stash` to temporarily save changes\n    Or run `git commit -am \"message\"` to commit changes\n    Or run `git checkout -- .` to discard changes (destructive)",
  "created_at": "2026-01-19T16:44:38.424Z",
  "updated_at": "2026-01-19T16:58:31.143Z",
  "problem_statement": "The codebase has two CLI commands ('idea' and 'ideas') that perform identical functionality, causing user confusion",
  "motivation": "Having two commands for the same purpose is confusing for users. Since the project hasn't reached 1.0 yet, it's safe to remove the duplicate command entirely.",
  "success_criteria": [
    "Only 'ideas' command exists in CLI",
    "All references to 'idea' command removed from codebase",
    "No breaking changes to existing functionality",
    "Documentation only references 'ideas' command"
  ],
  "technical_constraints": [
    "Must remove 'idea' command entirely from src/index.ts",
    "Cannot introduce breaking changes to the 'ideas' command functionality",
    "Tests must continue to pass"
  ],
  "scope_in_scope": [
    "Remove 'idea' command registration from CLI definition in src/index.ts",
    "Search codebase for any lingering references to 'idea' CLI command",
    "Update documentation if needed (README, AGENTS.md, etc.)",
    "Update any tests that reference the 'idea' command"
  ],
  "scope_out_of_scope": [
    "Changing the 'idea' state name used internally in the workflow",
    "Modifying the 'ideas' command functionality"
  ],
  "priority_hint": "medium",
  "urgency_hint": "low"
}
