{
  "schema_version": 1,
  "id": "003-add-guardrails-against-premature-code-changes-in-i",
  "title": "Add guardrails against premature code changes in idea agent",
  "section": "agent",
  "state": "implementing",
  "overview": "The idea agent went ahead and fixed an issue during the brainstorming process, which is unintended behavior. The idea stage should be about exploration and planning, not implementation.\n\n**Motivation:** Preserve the separation between idea brainstorming and implementation phases. Users may not expect code changes during ideation.\n\n**Success criteria:**\n- Idea agent checks for local changes in the codebase before proceeding\n- Warning shown to user if there are uncommitted changes\n- Guardrails prevent the agent from making code changes during brainstorm\n\n**Technical constraints:**\n- Check for local git changes before allowing modifications\n- Do not block workflow but show warnings to user\n- Add safeguards within idea agent to prevent code modification operations\n\n**Signals:** priority: medium",
  "branch": null,
  "pr_url": null,
  "pr_number": null,
  "last_error": "Git pre-flight check failed:\n\nâ€¢ There are uncommitted changes in the working directory\n    Run `git stash` to temporarily save changes\n    Or run `git commit -am \"message\"` to commit changes\n    Or run `git checkout -- .` to discard changes (destructive)",
  "created_at": "2026-01-19T17:05:24.608Z",
  "updated_at": "2026-01-19T17:12:37.669Z",
  "problem_statement": "The idea agent went ahead and fixed an issue during the brainstorming process, which is unintended behavior. The idea stage should be about exploration and planning, not implementation.",
  "motivation": "Preserve the separation between idea brainstorming and implementation phases. Users may not expect code changes during ideation.",
  "success_criteria": [
    "Idea agent checks for local changes in the codebase before proceeding",
    "Warning shown to user if there are uncommitted changes",
    "Guardrails prevent the agent from making code changes during brainstorm"
  ],
  "technical_constraints": [
    "Check for local git changes before allowing modifications",
    "Do not block workflow but show warnings to user",
    "Add safeguards within idea agent to prevent code modification operations"
  ],
  "priority_hint": "medium"
}
